django_easy_images-5.2.dist-info/METADATA
django_easy_images-5.2.dist-info/WHEEL
django_easy_images-5.2.dist-info/entry_points.txt
easy_images/__init__.py
easy_images/apps.py
easy_images/core.py
easy_images/engine.py
easy_images/management/__init__.py
easy_images/management/commands/__init__.py
easy_images/management/commands/build_img_queue.py
easy_images/management/commands/easy_images.py
easy_images/management/process_queue.py
easy_images/migrations/0001_initial.py
easy_images/migrations/__init__.py
easy_images/models.py
easy_images/options.py
easy_images/signals.py
easy_images/templatetags/__init__.py
easy_images/templatetags/easy_images.py
easy_images/types_.py
django_easy_images-5.2.dist-info/RECORD
