Metadata-Version: 2.1
Name: django-easy-images
Version: 5.2
Summary: Easily build responsive HTML `<img>` tags from Django images
Author-Email: Chris Beaven <smileychris@gmail.com>
License: MIT
Classifier: Development Status :: 3 - Alpha
Classifier: Environment :: Web Environment
Classifier: Intended Audience :: Developers
Classifier: License :: OSI Approved :: MIT License
Classifier: Framework :: Django
Classifier: Framework :: Django :: 4.2
Classifier: Framework :: Django :: 5.0
Classifier: Programming Language :: Python :: 3
Classifier: Programming Language :: Python :: 3.8
Classifier: Programming Language :: Python :: 3.9
Classifier: Programming Language :: Python :: 3.10
Classifier: Topic :: Software Development :: Libraries :: Python Modules
Project-URL: Repository, https://github.com/SmileyChris/django-easy-images
Project-URL: Docs, https://smileychris.github.io/django-easy-images/
Requires-Python: >=3.8
Requires-Dist: django>=4.2
Requires-Dist: typing-extensions>=4.11.0
Requires-Dist: django-stubs-ext>=4.2.7
Requires-Dist: pyvips>=2.2.2
Requires-Dist: tqdm>=4.66.2
Requires-Dist: pillow
Provides-Extra: tests
Requires-Dist: pytest; extra == "tests"
Requires-Dist: pytest-django>=4.8.0; extra == "tests"
